{
    "PXPMessagesData": {
        "attributes": {
            "xmlns:xsd": "http://www.w3.org/2001/XMLSchema",
            "xmlns:xsi": "http://www.w3.org/2001/XMLSchema-instance"
        },
        "MessageListings": [
            {
                "MessageListing": {
                    "attributes": {
                        "IconURL": "images/PXP/TchComment_S.gif",
                        "ID": "Test Message ID",
                        "BeginDate": "01/01/2020 12:00:00",
                        "Type": "StudentActivity",
                        "Subject": "Test Subject",
                        "Content": "Test Content"
                    }
                }
            }
        ]
    }
}
